{
  "multipart": [
    {
      "when": {
        "north": "false",
        "east": "false",
        "south": "false",
        "west": "false",
        "waterlogged": "false|true"
      },
      "apply": {
        "model": "chisel_legacy:block/glasspane_stained/red/brick/post"
      }
    },
    {
      "when": {
        "north": "true",
        "east": "false",
        "south": "false",
        "west": "false",
        "waterlogged": "false|true"
      },
      "apply": {
        "model": "chisel_legacy:block/glasspane_stained/red/brick/n"
      }
    },
    {
      "when": {
        "north": "false",
        "east": "true",
        "south": "false",
        "west": "false",
        "waterlogged": "false|true"
      },
      "apply": {
        "model": "chisel_legacy:block/glasspane_stained/red/brick/e"
      }
    },
    {
      "when": {
        "north": "false",
        "east": "false",
        "south": "true",
        "west": "false",
        "waterlogged": "false|true"
      },
      "apply": {
        "model": "chisel_legacy:block/glasspane_stained/red/brick/s"
      }
    },
    {
      "when": {
        "north": "false",
        "east": "false",
        "south": "false",
        "west": "true",
        "waterlogged": "false|true"
      },
      "apply": {
        "model": "chisel_legacy:block/glasspane_stained/red/brick/w"
      }
    },
    {
      "when": {
        "north": "true",
        "east": "true",
        "south": "false",
        "west": "false",
        "waterlogged": "false|true"
      },
      "apply": {
        "model": "chisel_legacy:block/glasspane_stained/red/brick/ne"
      }
    },
    {
      "when": {
        "north": "false",
        "east": "true",
        "south": "true",
        "west": "false",
        "waterlogged": "false|true"
      },
      "apply": {
        "model": "chisel_legacy:block/glasspane_stained/red/brick/se"
      }
    },
    {
      "when": {
        "north": "false",
        "east": "false",
        "south": "true",
        "west": "true",
        "waterlogged": "false|true"
      },
      "apply": {
        "model": "chisel_legacy:block/glasspane_stained/red/brick/sw"
      }
    },
    {
      "when": {
        "north": "true",
        "east": "false",
        "south": "false",
        "west": "true",
        "waterlogged": "false|true"
      },
      "apply": {
        "model": "chisel_legacy:block/glasspane_stained/red/brick/nw"
      }
    },
    {
      "when": {
        "north": "true",
        "east": "false",
        "south": "true",
        "west": "false",
        "waterlogged": "false|true"
      },
      "apply": {
        "model": "chisel_legacy:block/glasspane_stained/red/brick/ns"
      }
    },
    {
      "when": {
        "north": "false",
        "east": "true",
        "south": "false",
        "west": "true",
        "waterlogged": "false|true"
      },
      "apply": {
        "model": "chisel_legacy:block/glasspane_stained/red/brick/ew"
      }
    },
    {
      "when": {
        "north": "true",
        "east": "true",
        "south": "true",
        "west": "false",
        "waterlogged": "false|true"
      },
      "apply": {
        "model": "chisel_legacy:block/glasspane_stained/red/brick/nse"
      }
    },
    {
      "when": {
        "north": "false",
        "east": "true",
        "south": "true",
        "west": "true",
        "waterlogged": "false|true"
      },
      "apply": {
        "model": "chisel_legacy:block/glasspane_stained/red/brick/sew"
      }
    },
    {
      "when": {
        "north": "true",
        "east": "false",
        "south": "true",
        "west": "true",
        "waterlogged": "false|true"
      },
      "apply": {
        "model": "chisel_legacy:block/glasspane_stained/red/brick/nsw"
      }
    },
    {
      "when": {
        "north": "true",
        "east": "true",
        "south": "false",
        "west": "true",
        "waterlogged": "false|true"
      },
      "apply": {
        "model": "chisel_legacy:block/glasspane_stained/red/brick/new"
      }
    },
    {
      "when": {
        "north": "true",
        "east": "true",
        "south": "true",
        "west": "true",
        "waterlogged": "false|true"
      },
      "apply": {
        "model": "chisel_legacy:block/glasspane_stained/red/brick/nsew"
      }
    }
  ]
}